flutile/__init__.py
flutile/api.py
flutile/functions.py
flutile/motifs.py
flutile/parameters.py
flutile/py.typed
flutile/ui.py
flutile/version.py
flutile/data/a26-h1.txt
flutile/data/a26-h3.txt
flutile/data/a26-h5.txt
flutile/data/a26-h7.txt
flutile/data/a26-h9.txt
flutile/data/burke-phenotypes.txt
flutile/data/burke2014-index-map.txt
flutile/data/caton82.txt
flutile/data/h1-ha1-ref.faa
flutile/data/h3-ha1-ref.faa
flutile/data/h3-ref.faa
flutile/data/internal-refs.faa
flutile/data/internal-refs.fna
flutile/data/na-subtype-refs.faa
flutile/data/na-subtype-refs.fna
flutile/data/pdm-ref.faa
flutile/data/subtype-refs.faa
flutile/data/subtype-refs.fna
flutile/data/wiley81.txt
flutile-1.0.1.dist-info/LICENSE
flutile-1.0.1.dist-info/METADATA
flutile-1.0.1.dist-info/WHEEL
flutile-1.0.1.dist-info/entry_points.txt
flutile-1.0.1.dist-info/top_level.txt
flutile-1.0.1.dist-info/RECORD
