Metadata-Version: 2.1
Name: flutile
Version: 1.0.1
Summary: sequence analysis tools for flu research
Home-page: https://github.com/flu-crew/flutile
Author: Zebulun Arendsee
Author-email: zebulun.arendsee@usda.gov
License: UNKNOWN
Platform: UNKNOWN
Classifier: Programming Language :: Python :: 3
Classifier: License :: OSI Approved :: MIT License
Classifier: Operating System :: OS Independent
License-File: LICENSE
Requires-Dist: smof
Requires-Dist: biopython
Requires-Dist: click
Requires-Dist: tqdm
